puni/__init__.py
puni/base.py
puni/decorators.py
puni/version.py
puni-1.1.3.dist-info/LICENSE
puni-1.1.3.dist-info/METADATA
puni-1.1.3.dist-info/WHEEL
puni-1.1.3.dist-info/top_level.txt
puni-1.1.3.dist-info/RECORD
