Metadata-Version: 2.1
Name: puni
Version: 1.1.3
Summary: Python UserNotes Interface for reddit
Home-page: http://github.com/teaearlgraycold/puni
Author: teaearlgraycold
Author-email: UNKNOWN
License: GPLv3
Platform: UNKNOWN
Classifier: Development Status :: 5 - Production/Stable
Classifier: Environment :: Console
Classifier: Intended Audience :: Developers
Classifier: License :: OSI Approved :: GNU General Public License (GPL)
Classifier: Programming Language :: Python :: 2.7
Classifier: Programming Language :: Python :: 3.6
Classifier: Programming Language :: Python :: Implementation :: CPython
Classifier: Topic :: Utilities
Requires-Dist: praw (<=7.1.0,>=4.0)
